datasette_seaborn/__init__.py
datasette_seaborn/render.py
datasette_seaborn-0.2a0.dist-info/METADATA
datasette_seaborn-0.2a0.dist-info/WHEEL
datasette_seaborn-0.2a0.dist-info/entry_points.txt
datasette_seaborn-0.2a0.dist-info/top_level.txt
datasette_seaborn-0.2a0.dist-info/RECORD
