Metadata-Version: 2.1
Name: datasette-seaborn
Version: 0.2a0
Summary: Statistical visualizations for Datasette using Seaborn
Home-page: https://github.com/simonw/datasette-seaborn
Author: Simon Willison
License: Apache License, Version 2.0
Project-URL: Issues, https://github.com/simonw/datasette-seaborn/issues
Project-URL: CI, https://github.com/simonw/datasette-seaborn/actions
Project-URL: Changelog, https://github.com/simonw/datasette-seaborn/releases
Platform: UNKNOWN
Requires-Dist: datasette (>=0.50)
Requires-Dist: seaborn (>=0.11.0)
Provides-Extra: test
Requires-Dist: pytest ; extra == 'test'
Requires-Dist: pytest-asyncio ; extra == 'test'
